LICENSE.txt
MANIFEST.in
README.rst
REQUIREMENTS.txt
setup.cfg
setup.py
src/BJRobot/__init__.py
src/BJRobot/version.py
src/BJRobot/keywords/__init__.py
src/BJRobot/keywords/android_utils.py
src/BJRobot/keywords/applicationmanager.py
src/BJRobot/keywords/browsercache.py
src/BJRobot/keywords/browsermanager.py
src/BJRobot/keywords/element.py
src/BJRobot/keywords/keyevent.py
src/BJRobot/keywords/keywordgroup.py
src/BJRobot/keywords/logging.py
src/BJRobot/keywords/runonfailure.py
src/BJRobot/keywords/screenshot.py
src/BJRobot/keywords/touch.py
src/BJRobot/keywords/wait.py
src/BJRobot/log/chrome.log
src/BJRobot/log/edge.log
src/BJRobot/log/geckodriver.log
src/BJRobot/log/ie.log
src/BJRobot/resource/driver/chrome/2.27/linux32/chromedriver
src/BJRobot/resource/driver/chrome/2.27/linux64/chromedriver
src/BJRobot/resource/driver/chrome/2.27/mac64/chromedriver
src/BJRobot/resource/driver/chrome/2.27/win32/chromedriver.exe
src/BJRobot/resource/driver/edge/14393/MicrosoftWebDriver.exe
src/BJRobot/resource/driver/firefox/0.11.1/linux64/geckodriver
src/BJRobot/resource/driver/firefox/0.11.1/win32/geckodriver.exe
src/BJRobot/resource/driver/firefox/0.11.1/win64/geckodriver.exe
src/BJRobot/resource/driver/firefox/0.12/linux32/geckodriver
src/BJRobot/resource/driver/firefox/0.12/linux64/geckodriver
src/BJRobot/resource/driver/firefox/0.12/win32/geckodriver.exe
src/BJRobot/resource/driver/firefox/0.12/win64/geckodriver.exe
src/BJRobot/resource/driver/ie/2.53/win32/IEDriverServer.exe
src/BJRobot/resource/driver/ie/2.53/win64/IEDriverServer.exe
src/BJRobot/settings/platform.cfg
src/BJRobot/utilities/__init__.py
src/BJRobot/utilities/system.py
src/robotframework_bjrobot.egg-info/PKG-INFO
src/robotframework_bjrobot.egg-info/SOURCES.txt
src/robotframework_bjrobot.egg-info/dependency_links.txt
src/robotframework_bjrobot.egg-info/requires.txt
src/robotframework_bjrobot.egg-info/top_level.txt