Metadata-Version: 1.0
Name: robotframework-bjrobot
Version: 0.6.4
Summary: BJRobot is a web testing library for Robot Framework
Home-page: https://github.com/overfly83/bjrobot
Author: edward zhang
Author-email: zhl830905@hotmail.com
License: Apache License 2.0
Platform: any
